{"95":{"maxcombo":645,"statistics":{"count_100":25,"count_300":423,"count_50":3,"count_geki":773,"count_katu":129,"count_miss":5},"user_id":3597096,"score_id":203708188,"rank":"S","pp":81.0466},"96":{"maxcombo":650,"statistics":{"count_100":17,"count_300":364,"count_50":0,"count_geki":879,"count_katu":84,"count_miss":14},"user_id":4393263,"score_id":444363057,"rank":"S","pp":90.2755},"97":{"maxcombo":850,"statistics":{"count_100":12,"count_300":433,"count_50":1,"count_geki":830,"count_katu":76,"count_miss":6},"user_id":12002361,"score_id":390753210,"rank":"S","pp":94.6471},"98.8":{"maxcombo":677,"statistics":{"count_100":3,"count_300":374,"count_50":0,"count_geki":946,"count_katu":32,"count_miss":3},"user_id":3996030,"score_id":393842500,"rank":"S","pp":108.881},"97.4":{"maxcombo":1579,"statistics":{"count_100":6,"count_300":448,"count_50":3,"count_geki":817,"count_katu":84,"count_miss":0},"user_id":30112399,"score_id":505111282,"rank":"S","pp":96.7666},"96.9":{"maxcombo":663,"statistics":{"count_100":9,"count_300":322,"count_50":2,"count_geki":944,"count_katu":71,"count_miss":10},"user_id":13254473,"score_id":535085453,"rank":"S","pp":97.4879},"97.1":{"maxcombo":1592,"statistics":{"count_100":8,"count_300":527,"count_50":2,"count_geki":726,"count_katu":95,"count_miss":0},"user_id":15284515,"score_id":505130840,"rank":"S","pp":92.2479},"96.1":{"maxcombo":806,"statistics":{"count_100":13,"count_300":456,"count_50":1,"count_geki":760,"count_katu":127,"count_miss":1},"user_id":19604910,"score_id":542687687,"rank":"S","pp":86.9931},"98.1":{"maxcombo":900,"statistics":{"count_100":4,"count_300":439,"count_50":1,"count_geki":850,"count_katu":63,"count_miss":1},"user_id":15399579,"score_id":521616615,"rank":"S","pp":101.712},"95.9":{"maxcombo":648,"statistics":{"count_100":17,"count_300":419,"count_50":2,"count_geki":808,"count_katu":104,"count_miss":8},"user_id":9462800,"score_id":424410385,"rank":"S","pp":87.155},"95.5":{"maxcombo":1164,"statistics":{"count_100":18,"count_300":405,"count_50":0,"count_geki":792,"count_katu":142,"count_miss":1},"user_id":32042770,"score_id":541896175,"rank":"S","pp":84.6233},"96.2":{"maxcombo":675,"statistics":{"count_100":17,"count_300":388,"count_50":1,"count_geki":859,"count_katu":81,"count_miss":12},"user_id":24214485,"score_id":539959129,"rank":"S","pp":90.6435},"98.2":{"maxcombo":1324,"statistics":{"count_100":6,"count_300":374,"count_50":0,"count_geki":924,"count_katu":51,"count_miss":3},"user_id":24133683,"score_id":533123485,"rank":"S","pp":104.553},"96.7":{"maxcombo":663,"statistics":{"count_100":15,"count_300":346,"count_50":0,"count_geki":908,"count_katu":82,"count_miss":7},"user_id":18173287,"score_id":514270864,"rank":"S","pp":95.1034},"95.1":{"maxcombo":319,"statistics":{"count_100":22,"count_300":398,"count_50":1,"count_geki":834,"count_katu":78,"count_miss":25},"user_id":9314504,"score_id":389356645,"rank":"S","pp":83.1367},"94.2":{"maxcombo":282,"statistics":{"count_100":29,"count_300":414,"count_50":11,"count_geki":776,"count_katu":118,"count_miss":10},"user_id":14176480,"score_id":527416240,"rank":"A","pp":76.4248},"94.5":{"maxcombo":386,"statistics":{"count_100":25,"count_300":472,"count_50":4,"count_geki":732,"count_katu":106,"count_miss":19},"user_id":30967594,"score_id":539753776,"rank":"A","pp":76.675},"96.4":{"maxcombo":405,"statistics":{"count_100":9,"count_300":414,"count_50":6,"count_geki":839,"count_katu":80,"count_miss":10},"user_id":13439372,"score_id":534226727,"rank":"S","pp":91.6002},"96.5":{"maxcombo":664,"statistics":{"count_100":10,"count_300":371,"count_50":1,"count_geki":879,"count_katu":86,"count_miss":11},"user_id":21187195,"score_id":512805520,"rank":"S","pp":92.9985},"95.6":{"maxcombo":283,"statistics":{"count_100":16,"count_300":414,"count_50":4,"count_geki":816,"count_katu":94,"count_miss":14},"user_id":6341686,"score_id":303616851,"rank":"S","pp":85.7714},"93.9":{"maxcombo":565,"statistics":{"count_100":30,"count_300":541,"count_50":2,"count_geki":629,"count_katu":143,"count_miss":13},"user_id":1688669,"score_id":329074617,"rank":"A","pp":70.1102},"93.8":{"maxcombo":793,"statistics":{"count_100":39,"count_300":428,"count_50":0,"count_geki":730,"count_katu":155,"count_miss":6},"user_id":8023626,"score_id":335017199,"rank":"A","pp":72.4948},"95.7":{"maxcombo":573,"statistics":{"count_100":13,"count_300":424,"count_50":2,"count_geki":795,"count_katu":114,"count_miss":10},"user_id":3930357,"score_id":504069640,"rank":"S","pp":85.5948},"91.8":{"maxcombo":265,"statistics":{"count_100":33,"count_300":447,"count_50":9,"count_geki":672,"count_katu":174,"count_miss":23},"user_id":3599087,"score_id":342962797,"rank":"A","pp":58.9385},"93.5":{"maxcombo":660,"statistics":{"count_100":30,"count_300":522,"count_50":1,"count_geki":631,"count_katu":160,"count_miss":14},"user_id":8929283,"score_id":394789988,"rank":"A","pp":67.5933},"93.1":{"maxcombo":360,"statistics":{"count_100":31,"count_300":388,"count_50":6,"count_geki":757,"count_katu":162,"count_miss":14},"user_id":5217719,"score_id":477355073,"rank":"A","pp":68.8739},"92.9":{"maxcombo":661,"statistics":{"count_100":46,"count_300":529,"count_50":0,"count_geki":609,"count_katu":163,"count_miss":11},"user_id":30695491,"score_id":518659331,"rank":"A","pp":63.4866}}