{"99.1":{"maxcombo":545,"statistics":{"count_100":9,"count_300":536,"count_50":0,"count_geki":14,"count_katu":1,"count_miss":0},"user_id":9354008,"score_id":150108299,"rank":"S","pp":152.35},"99.5":{"maxcombo":545,"statistics":{"count_100":5,"count_300":540,"count_50":0,"count_geki":15,"count_katu":0,"count_miss":0},"user_id":8266817,"score_id":157326518,"rank":"S","pp":155.127},"99.7":{"maxcombo":545,"statistics":{"count_100":3,"count_300":542,"count_50":0,"count_geki":18,"count_katu":0,"count_miss":0},"user_id":5622583,"score_id":144301576,"rank":"S","pp":156.538}}