{"93":{"maxcombo":567,"statistics":{"count_100":151,"count_300":1152,"count_50":0,"count_geki":3,"count_katu":0,"count_miss":16},"user_id":14220218,"score_id":170143069,"rank":"B","pp":155.662},"94":{"maxcombo":982,"statistics":{"count_100":154,"count_300":1163,"count_50":0,"count_geki":12,"count_katu":0,"count_miss":2},"user_id":14759830,"score_id":164495241,"rank":"B","pp":184.803},"95":{"maxcombo":326,"statistics":{"count_100":108,"count_300":1200,"count_50":0,"count_geki":47,"count_katu":5,"count_miss":11},"user_id":12941916,"score_id":157874956,"rank":"A","pp":177.99},"96":{"maxcombo":809,"statistics":{"count_100":97,"count_300":1218,"count_50":0,"count_geki":0,"count_katu":0,"count_miss":4},"user_id":14019041,"score_id":155162048,"rank":"A","pp":197.554},"97":{"maxcombo":592,"statistics":{"count_100":57,"count_300":1252,"count_50":0,"count_geki":6,"count_katu":1,"count_miss":10},"user_id":10085764,"score_id":167105667,"rank":"A","pp":196.431},"98":{"maxcombo":693,"statistics":{"count_100":45,"count_300":1271,"count_50":0,"count_geki":38,"count_katu":2,"count_miss":3},"user_id":2240311,"score_id":157978083,"rank":"A","pp":217.948},"99":{"maxcombo":1319,"statistics":{"count_100":26,"count_300":1293,"count_50":0,"count_geki":2,"count_katu":0,"count_miss":0},"user_id":13171189,"score_id":154305274,"rank":"S","pp":233.175},"98.5":{"maxcombo":1319,"statistics":{"count_100":39,"count_300":1280,"count_50":0,"count_geki":6,"count_katu":0,"count_miss":0},"user_id":556074,"score_id":155697287,"rank":"S","pp":228.196},"98.9":{"maxcombo":1319,"statistics":{"count_100":28,"count_300":1291,"count_50":0,"count_geki":52,"count_katu":1,"count_miss":0},"user_id":10528333,"score_id":154418115,"rank":"S","pp":232.4},"98.8":{"maxcombo":1319,"statistics":{"count_100":31,"count_300":1288,"count_50":0,"count_geki":50,"count_katu":1,"count_miss":0},"user_id":15048710,"score_id":160301876,"rank":"S","pp":231.243},"96.3":{"maxcombo":820,"statistics":{"count_100":93,"count_300":1225,"count_50":0,"count_geki":4,"count_katu":0,"count_miss":1},"user_id":12609360,"score_id":167195233,"rank":"A","pp":206.343},"97.5":{"maxcombo":941,"statistics":{"count_100":62,"count_300":1256,"count_50":0,"count_geki":0,"count_katu":0,"count_miss":1},"user_id":2563453,"score_id":156645297,"rank":"A","pp":217.06},"97.7":{"maxcombo":1319,"statistics":{"count_100":59,"count_300":1260,"count_50":0,"count_geki":44,"count_katu":2,"count_miss":0},"user_id":4701806,"score_id":163249936,"rank":"S","pp":220.797},"98.6":{"maxcombo":1319,"statistics":{"count_100":35,"count_300":1284,"count_50":0,"count_geki":9,"count_katu":0,"count_miss":0},"user_id":9435841,"score_id":178785837,"rank":"S","pp":229.713},"98.4":{"maxcombo":1319,"statistics":{"count_100":41,"count_300":1278,"count_50":0,"count_geki":7,"count_katu":0,"count_miss":0},"user_id":1068275,"score_id":154105822,"rank":"S","pp":227.442},"97.1":{"maxcombo":1284,"statistics":{"count_100":73,"count_300":1245,"count_50":0,"count_geki":3,"count_katu":0,"count_miss":1},"user_id":10682737,"score_id":159741915,"rank":"A","pp":213.177},"97.9":{"maxcombo":821,"statistics":{"count_100":51,"count_300":1267,"count_50":0,"count_geki":26,"count_katu":1,"count_miss":1},"user_id":8090603,"score_id":162946259,"rank":"A","pp":221.034},"96.9":{"maxcombo":820,"statistics":{"count_100":77,"count_300":1240,"count_50":0,"count_geki":1,"count_katu":0,"count_miss":2},"user_id":4175623,"score_id":154119850,"rank":"A","pp":209.213},"99.2":{"maxcombo":1319,"statistics":{"count_100":21,"count_300":1298,"count_50":0,"count_geki":51,"count_katu":1,"count_miss":0},"user_id":7958845,"score_id":156741527,"rank":"S","pp":235.127},"97.8":{"maxcombo":1319,"statistics":{"count_100":57,"count_300":1262,"count_50":0,"count_geki":11,"count_katu":1,"count_miss":0},"user_id":7916838,"score_id":158032577,"rank":"S","pp":221.523},"98.1":{"maxcombo":899,"statistics":{"count_100":38,"count_300":1276,"count_50":0,"count_geki":13,"count_katu":1,"count_miss":5},"user_id":978707,"score_id":155876906,"rank":"A","pp":215.328},"98.7":{"maxcombo":1319,"statistics":{"count_100":33,"count_300":1286,"count_50":0,"count_geki":0,"count_katu":0,"count_miss":0},"user_id":12756108,"score_id":179124534,"rank":"S","pp":230.477},"97.4":{"maxcombo":1057,"statistics":{"count_100":63,"count_300":1254,"count_50":0,"count_geki":0,"count_katu":0,"count_miss":2},"user_id":16701256,"score_id":167071331,"rank":"A","pp":214.09},"95.1":{"maxcombo":1011,"statistics":{"count_100":115,"count_300":1198,"count_50":0,"count_geki":38,"count_katu":5,"count_miss":6},"user_id":16542398,"score_id":177619802,"rank":"A","pp":187.126},"95.6":{"maxcombo":672,"statistics":{"count_100":73,"count_300":1225,"count_50":0,"count_geki":4,"count_katu":0,"count_miss":21},"user_id":13656706,"score_id":176062296,"rank":"A","pp":167.652},"96.7":{"maxcombo":1319,"statistics":{"count_100":85,"count_300":1234,"count_50":0,"count_geki":33,"count_katu":1,"count_miss":0},"user_id":8504794,"score_id":164149034,"rank":"S","pp":211.631},"96.5":{"maxcombo":564,"statistics":{"count_100":72,"count_300":1237,"count_50":0,"count_geki":0,"count_katu":0,"count_miss":10},"user_id":12659195,"score_id":179615813,"rank":"A","pp":191.466},"96.4":{"maxcombo":893,"statistics":{"count_100":66,"count_300":1239,"count_50":0,"count_geki":23,"count_katu":1,"count_miss":14},"user_id":7812292,"score_id":156954546,"rank":"A","pp":184.411},"95.7":{"maxcombo":778,"statistics":{"count_100":103,"count_300":1212,"count_50":0,"count_geki":0,"count_katu":0,"count_miss":4},"user_id":12365660,"score_id":158013451,"rank":"A","pp":195.623},"96.6":{"maxcombo":495,"statistics":{"count_100":72,"count_300":1239,"count_50":0,"count_geki":37,"count_katu":0,"count_miss":8},"user_id":16827819,"score_id":164364378,"rank":"A","pp":196.135},"97.6":{"maxcombo":538,"statistics":{"count_100":45,"count_300":1265,"count_50":0,"count_geki":15,"count_katu":0,"count_miss":9},"user_id":5378397,"score_id":173802006,"rank":"A","pp":202.909},"95.9":{"maxcombo":788,"statistics":{"count_100":83,"count_300":1224,"count_50":0,"count_geki":0,"count_katu":0,"count_miss":12},"user_id":9521654,"score_id":154889999,"rank":"A","pp":183.44},"94.6":{"maxcombo":886,"statistics":{"count_100":135,"count_300":1181,"count_50":0,"count_geki":3,"count_katu":1,"count_miss":3},"user_id":18003502,"score_id":158091908,"rank":"B","pp":188.081},"97.2":{"maxcombo":473,"statistics":{"count_100":48,"count_300":1259,"count_50":0,"count_geki":0,"count_katu":0,"count_miss":12},"user_id":4313928,"score_id":177396370,"rank":"A","pp":194.822},"93.6":{"maxcombo":404,"statistics":{"count_100":140,"count_300":1165,"count_50":0,"count_geki":42,"count_katu":6,"count_miss":14},"user_id":16547923,"score_id":160323848,"rank":"B","pp":162.557},"94.7":{"maxcombo":497,"statistics":{"count_100":115,"count_300":1192,"count_50":0,"count_geki":5,"count_katu":2,"count_miss":12},"user_id":21920505,"score_id":163223061,"rank":"A","pp":173.763},"95.5":{"maxcombo":317,"statistics":{"count_100":77,"count_300":1222,"count_50":0,"count_geki":2,"count_katu":0,"count_miss":20},"user_id":1255834,"score_id":168879659,"rank":"A","pp":168.448},"95.4":{"maxcombo":377,"statistics":{"count_100":79,"count_300":1219,"count_50":0,"count_geki":0,"count_katu":1,"count_miss":21},"user_id":4586549,"score_id":155065467,"rank":"A","pp":165.874},"96.2":{"maxcombo":544,"statistics":{"count_100":65,"count_300":1237,"count_50":0,"count_geki":10,"count_katu":0,"count_miss":17},"user_id":112408,"score_id":162194587,"rank":"A","pp":178.272},"94.2":{"maxcombo":335,"statistics":{"count_100":117,"count_300":1185,"count_50":0,"count_geki":15,"count_katu":2,"count_miss":17},"user_id":13094254,"score_id":161003794,"rank":"B","pp":162.886},"94.9":{"maxcombo":394,"statistics":{"count_100":107,"count_300":1199,"count_50":0,"count_geki":0,"count_katu":0,"count_miss":13},"user_id":7934265,"score_id":163572344,"rank":"A","pp":173.98},"93.7":{"maxcombo":571,"statistics":{"count_100":120,"count_300":1177,"count_50":0,"count_geki":16,"count_katu":3,"count_miss":22},"user_id":11113772,"score_id":161886025,"rank":"B","pp":152.477},"93.1":{"maxcombo":416,"statistics":{"count_100":152,"count_300":1153,"count_50":0,"count_geki":9,"count_katu":3,"count_miss":14},"user_id":6781062,"score_id":155243356,"rank":"B","pp":159.332},"92.1":{"maxcombo":408,"statistics":{"count_100":154,"count_300":1138,"count_50":0,"count_geki":0,"count_katu":0,"count_miss":27},"user_id":30236198,"score_id":178722375,"rank":"B","pp":135.152},"94.5":{"maxcombo":192,"statistics":{"count_100":85,"count_300":1204,"count_50":0,"count_geki":32,"count_katu":0,"count_miss":30},"user_id":7165787,"score_id":177559496,"rank":"A","pp":147.577},"91.7":{"maxcombo":233,"statistics":{"count_100":189,"count_300":1116,"count_50":0,"count_geki":0,"count_katu":0,"count_miss":14},"user_id":1593473,"score_id":161510436,"rank":"B","pp":149.896},"92.8":{"maxcombo":363,"statistics":{"count_100":116,"count_300":1167,"count_50":0,"count_geki":0,"count_katu":0,"count_miss":36},"user_id":24750511,"score_id":178613777,"rank":"B","pp":129.866},"88.4":{"maxcombo":331,"statistics":{"count_100":253,"count_300":1040,"count_50":0,"count_geki":18,"count_katu":7,"count_miss":26},"user_id":1418541,"score_id":154111626,"rank":"C","pp":115.556},"90.9":{"maxcombo":304,"statistics":{"count_100":202,"count_300":1098,"count_50":0,"count_geki":0,"count_katu":0,"count_miss":19},"user_id":13257511,"score_id":155416244,"rank":"B","pp":137.647},"94.1":{"maxcombo":383,"statistics":{"count_100":113,"count_300":1185,"count_50":0,"count_geki":7,"count_katu":0,"count_miss":21},"user_id":16490362,"score_id":178477000,"rank":"B","pp":156.235},"89.9":{"maxcombo":173,"statistics":{"count_100":161,"count_300":1106,"count_50":0,"count_geki":0,"count_katu":0,"count_miss":52},"user_id":4261784,"score_id":157769467,"rank":"B","pp":98.6556},"91.2":{"maxcombo":341,"statistics":{"count_100":190,"count_300":1109,"count_50":0,"count_geki":0,"count_katu":0,"count_miss":20},"user_id":17287063,"score_id":154396441,"rank":"B","pp":138.654},"93.2":{"maxcombo":209,"statistics":{"count_100":121,"count_300":1169,"count_50":0,"count_geki":3,"count_katu":0,"count_miss":29},"user_id":4379575,"score_id":173597686,"rank":"B","pp":139.878},"91.8":{"maxcombo":295,"statistics":{"count_100":121,"count_300":1151,"count_50":0,"count_geki":0,"count_katu":0,"count_miss":47},"user_id":5513495,"score_id":178708744,"rank":"B","pp":113.059}}