{"94":{"maxcombo":337,"statistics":{"count_100":85,"count_300":986,"count_50":0,"count_geki":7,"count_katu":3,"count_miss":23},"user_id":25017421,"score_id":173051873,"rank":"A","pp":111.742},"96":{"maxcombo":769,"statistics":{"count_100":71,"count_300":1015,"count_50":0,"count_geki":35,"count_katu":1,"count_miss":8},"user_id":24862497,"score_id":173585997,"rank":"A","pp":138.924},"97":{"maxcombo":1094,"statistics":{"count_100":65,"count_300":1029,"count_50":0,"count_geki":72,"count_katu":2,"count_miss":0},"user_id":7643000,"score_id":169429557,"rank":"S","pp":155.553},"98":{"maxcombo":733,"statistics":{"count_100":40,"count_300":1053,"count_50":0,"count_geki":71,"count_katu":2,"count_miss":1},"user_id":20171664,"score_id":176516899,"rank":"A","pp":161.894},"99":{"maxcombo":1094,"statistics":{"count_100":21,"count_300":1073,"count_50":0,"count_geki":0,"count_katu":0,"count_miss":0},"user_id":15289838,"score_id":179490434,"rank":"S","pp":170.638},"99.4":{"maxcombo":1094,"statistics":{"count_100":13,"count_300":1081,"count_50":0,"count_geki":0,"count_katu":0,"count_miss":0},"user_id":32059557,"score_id":179180642,"rank":"S","pp":173.574},"99.7":{"maxcombo":1094,"statistics":{"count_100":6,"count_300":1088,"count_50":0,"count_geki":24,"count_katu":0,"count_miss":0},"user_id":9656842,"score_id":172785194,"rank":"S","pp":176.194},"98.2":{"maxcombo":1094,"statistics":{"count_100":39,"count_300":1055,"count_50":0,"count_geki":29,"count_katu":0,"count_miss":0},"user_id":21073612,"score_id":170609343,"rank":"S","pp":164.255},"99.5":{"maxcombo":1094,"statistics":{"count_100":9,"count_300":1085,"count_50":0,"count_geki":4,"count_katu":0,"count_miss":0},"user_id":24584522,"score_id":169633794,"rank":"S","pp":175.065},"97.6":{"maxcombo":590,"statistics":{"count_100":48,"count_300":1044,"count_50":0,"count_geki":0,"count_katu":0,"count_miss":2},"user_id":22310185,"score_id":177939055,"rank":"A","pp":157.218},"95.5":{"maxcombo":308,"statistics":{"count_100":83,"count_300":1004,"count_50":0,"count_geki":70,"count_katu":2,"count_miss":7},"user_id":24225287,"score_id":170593377,"rank":"A","pp":137.136},"97.8":{"maxcombo":1094,"statistics":{"count_100":46,"count_300":1048,"count_50":0,"count_geki":37,"count_katu":4,"count_miss":0},"user_id":16714586,"score_id":177656631,"rank":"S","pp":161.853},"99.1":{"maxcombo":1094,"statistics":{"count_100":18,"count_300":1076,"count_50":0,"count_geki":67,"count_katu":1,"count_miss":0},"user_id":13336727,"score_id":171980572,"rank":"S","pp":171.732},"98.3":{"maxcombo":1094,"statistics":{"count_100":36,"count_300":1058,"count_50":0,"count_geki":10,"count_katu":0,"count_miss":0},"user_id":1373019,"score_id":174395955,"rank":"S","pp":165.298},"99.2":{"maxcombo":1094,"statistics":{"count_100":17,"count_300":1077,"count_50":0,"count_geki":7,"count_katu":0,"count_miss":0},"user_id":18843245,"score_id":172341897,"rank":"S","pp":172.098},"98.4":{"maxcombo":1094,"statistics":{"count_100":34,"count_300":1060,"count_50":0,"count_geki":53,"count_katu":0,"count_miss":0},"user_id":17129354,"score_id":169452526,"rank":"S","pp":165.998},"98.7":{"maxcombo":1094,"statistics":{"count_100":27,"count_300":1067,"count_50":0,"count_geki":33,"count_katu":0,"count_miss":0},"user_id":14021759,"score_id":169433419,"rank":"S","pp":168.476},"99.3":{"maxcombo":1094,"statistics":{"count_100":15,"count_300":1079,"count_50":0,"count_geki":25,"count_katu":2,"count_miss":0},"user_id":17414986,"score_id":172790964,"rank":"S","pp":172.834},"98.6":{"maxcombo":1094,"statistics":{"count_100":30,"count_300":1064,"count_50":0,"count_geki":15,"count_katu":0,"count_miss":0},"user_id":16205636,"score_id":169584015,"rank":"S","pp":167.409},"96.4":{"maxcombo":783,"statistics":{"count_100":66,"count_300":1022,"count_50":0,"count_geki":18,"count_katu":1,"count_miss":6},"user_id":32453497,"score_id":176769717,"rank":"A","pp":143.971},"97.5":{"maxcombo":1094,"statistics":{"count_100":54,"count_300":1040,"count_50":0,"count_geki":16,"count_katu":0,"count_miss":0},"user_id":20503103,"score_id":177222904,"rank":"S","pp":159.162},"98.9":{"maxcombo":1094,"statistics":{"count_100":22,"count_300":1072,"count_50":0,"count_geki":51,"count_katu":0,"count_miss":0},"user_id":9638789,"score_id":170408127,"rank":"S","pp":170.275},"98.5":{"maxcombo":284,"statistics":{"count_100":22,"count_300":1067,"count_50":0,"count_geki":7,"count_katu":0,"count_miss":5},"user_id":6054853,"score_id":171151402,"rank":"A","pp":160.209},"97.7":{"maxcombo":1094,"statistics":{"count_100":50,"count_300":1044,"count_50":0,"count_geki":10,"count_katu":0,"count_miss":0},"user_id":10107187,"score_id":175687842,"rank":"S","pp":160.501},"98.8":{"maxcombo":1094,"statistics":{"count_100":26,"count_300":1068,"count_50":0,"count_geki":7,"count_katu":0,"count_miss":0},"user_id":3164701,"score_id":178673458,"rank":"S","pp":168.834},"99.9":{"maxcombo":1094,"statistics":{"count_100":2,"count_300":1092,"count_50":0,"count_geki":63,"count_katu":0,"count_miss":0},"user_id":5268367,"score_id":171059781,"rank":"S","pp":177.713},"96.9":{"maxcombo":649,"statistics":{"count_100":53,"count_300":1034,"count_50":0,"count_geki":0,"count_katu":0,"count_miss":7},"user_id":15513319,"score_id":170894590,"rank":"A","pp":146.202},"96.2":{"maxcombo":663,"statistics":{"count_100":67,"count_300":1019,"count_50":0,"count_geki":0,"count_katu":0,"count_miss":8},"user_id":25508193,"score_id":170714318,"rank":"A","pp":140.119},"97.1":{"maxcombo":720,"statistics":{"count_100":57,"count_300":1034,"count_50":0,"count_geki":37,"count_katu":1,"count_miss":3},"user_id":15150996,"score_id":175464354,"rank":"A","pp":152.348},"96.5":{"maxcombo":720,"statistics":{"count_100":64,"count_300":1024,"count_50":0,"count_geki":6,"count_katu":0,"count_miss":6},"user_id":15939435,"score_id":172949774,"rank":"A","pp":144.586},"97.4":{"maxcombo":535,"statistics":{"count_100":45,"count_300":1044,"count_50":0,"count_geki":85,"count_katu":4,"count_miss":5},"user_id":16327110,"score_id":171392382,"rank":"A","pp":152.458},"96.8":{"maxcombo":1094,"statistics":{"count_100":68,"count_300":1026,"count_50":0,"count_geki":48,"count_katu":2,"count_miss":0},"user_id":20057468,"score_id":178899913,"rank":"S","pp":154.587},"98.1":{"maxcombo":1094,"statistics":{"count_100":41,"count_300":1053,"count_50":0,"count_geki":0,"count_katu":0,"count_miss":0},"user_id":29279366,"score_id":179680972,"rank":"S","pp":163.564},"97.9":{"maxcombo":587,"statistics":{"count_100":41,"count_300":1051,"count_50":0,"count_geki":27,"count_katu":0,"count_miss":2},"user_id":28339022,"score_id":170395237,"rank":"A","pp":159.567},"97.3":{"maxcombo":862,"statistics":{"count_100":49,"count_300":1041,"count_50":0,"count_geki":0,"count_katu":0,"count_miss":4},"user_id":10986904,"score_id":176208603,"rank":"A","pp":153.041},"96.1":{"maxcombo":300,"statistics":{"count_100":51,"count_300":1026,"count_50":0,"count_geki":3,"count_katu":0,"count_miss":17},"user_id":10819779,"score_id":175827261,"rank":"A","pp":129.855},"96.3":{"maxcombo":306,"statistics":{"count_100":50,"count_300":1029,"count_50":0,"count_geki":3,"count_katu":1,"count_miss":15},"user_id":15515509,"score_id":169504378,"rank":"A","pp":133.366},"95.9":{"maxcombo":262,"statistics":{"count_100":43,"count_300":1028,"count_50":0,"count_geki":10,"count_katu":3,"count_miss":23},"user_id":19976182,"score_id":169591460,"rank":"A","pp":122.95},"95.6":{"maxcombo":1094,"statistics":{"count_100":96,"count_300":998,"count_50":0,"count_geki":26,"count_katu":0,"count_miss":0},"user_id":16791965,"score_id":178952758,"rank":"S","pp":145.924},"94.3":{"maxcombo":330,"statistics":{"count_100":71,"count_300":997,"count_50":0,"count_geki":4,"count_katu":0,"count_miss":26},"user_id":11081750,"score_id":169897739,"rank":"A","pp":111.162},"97.2":{"maxcombo":934,"statistics":{"count_100":53,"count_300":1037,"count_50":0,"count_geki":0,"count_katu":0,"count_miss":4},"user_id":18451684,"score_id":171058071,"rank":"A","pp":151.744},"94.8":{"maxcombo":506,"statistics":{"count_100":81,"count_300":997,"count_50":0,"count_geki":0,"count_katu":0,"count_miss":16},"user_id":9794768,"score_id":169454039,"rank":"A","pp":123.008},"96.7":{"maxcombo":669,"statistics":{"count_100":69,"count_300":1024,"count_50":0,"count_geki":11,"count_katu":1,"count_miss":1},"user_id":32480650,"score_id":176906103,"rank":"A","pp":152.333},"94.2":{"maxcombo":487,"statistics":{"count_100":115,"count_300":974,"count_50":0,"count_geki":0,"count_katu":0,"count_miss":5},"user_id":15293428,"score_id":179758743,"rank":"B","pp":131.587},"96.6":{"maxcombo":533,"statistics":{"count_100":60,"count_300":1027,"count_50":0,"count_geki":0,"count_katu":0,"count_miss":7},"user_id":19078659,"score_id":170461569,"rank":"A","pp":144.021},"95.7":{"maxcombo":516,"statistics":{"count_100":66,"count_300":1015,"count_50":0,"count_geki":0,"count_katu":0,"count_miss":13},"user_id":15140766,"score_id":179198409,"rank":"A","pp":131.953},"93.4":{"maxcombo":612,"statistics":{"count_100":121,"count_300":962,"count_50":0,"count_geki":0,"count_katu":0,"count_miss":11},"user_id":13892296,"score_id":174380755,"rank":"B","pp":120.267},"87.8":{"maxcombo":317,"statistics":{"count_100":246,"count_300":838,"count_50":0,"count_geki":5,"count_katu":1,"count_miss":10},"user_id":28237707,"score_id":171897738,"rank":"C","pp":94.6392},"94.9":{"maxcombo":353,"statistics":{"count_100":79,"count_300":999,"count_50":0,"count_geki":0,"count_katu":0,"count_miss":16},"user_id":16370452,"score_id":179203678,"rank":"A","pp":123.55},"91.4":{"maxcombo":258,"statistics":{"count_100":147,"count_300":927,"count_50":0,"count_geki":10,"count_katu":0,"count_miss":20},"user_id":13550004,"score_id":169690250,"rank":"B","pp":101.284},"94.6":{"maxcombo":469,"statistics":{"count_100":98,"count_300":987,"count_50":0,"count_geki":59,"count_katu":9,"count_miss":9},"user_id":12573425,"score_id":176297437,"rank":"A","pp":129.524},"90.1":{"maxcombo":244,"statistics":{"count_100":143,"count_300":915,"count_50":0,"count_geki":0,"count_katu":0,"count_miss":36},"user_id":25184098,"score_id":169887709,"rank":"B","pp":83.1633},"94.4":{"maxcombo":284,"statistics":{"count_100":87,"count_300":990,"count_50":0,"count_geki":39,"count_katu":4,"count_miss":17},"user_id":8190804,"score_id":170332034,"rank":"A","pp":119.89},"89.6":{"maxcombo":129,"statistics":{"count_100":154,"count_300":904,"count_50":0,"count_geki":0,"count_katu":0,"count_miss":36},"user_id":19223762,"score_id":172251448,"rank":"B","pp":81.0993},"92.7":{"maxcombo":267,"statistics":{"count_100":105,"count_300":962,"count_50":0,"count_geki":47,"count_katu":3,"count_miss":27},"user_id":18158906,"score_id":169615539,"rank":"B","pp":101.611}}