{"96":{"maxcombo":798,"statistics":{"count_100":63,"count_300":735,"count_50":0,"count_geki":0,"count_katu":0,"count_miss":0},"user_id":30130701,"score_id":174969255,"rank":"S","pp":92.9509},"98":{"maxcombo":798,"statistics":{"count_100":31,"count_300":767,"count_50":0,"count_geki":0,"count_katu":0,"count_miss":0},"user_id":20521798,"score_id":177027138,"rank":"S","pp":104.814},"96.1":{"maxcombo":798,"statistics":{"count_100":61,"count_300":737,"count_50":0,"count_geki":0,"count_katu":0,"count_miss":0},"user_id":9739785,"score_id":145252077,"rank":"S","pp":93.6473},"97.2":{"maxcombo":798,"statistics":{"count_100":44,"count_300":754,"count_50":0,"count_geki":0,"count_katu":0,"count_miss":0},"user_id":26750315,"score_id":176152293,"rank":"S","pp":99.8048},"96.9":{"maxcombo":577,"statistics":{"count_100":37,"count_300":755,"count_50":0,"count_geki":0,"count_katu":0,"count_miss":6},"user_id":12532553,"score_id":141710710,"rank":"A","pp":94.3274},"90.6":{"maxcombo":410,"statistics":{"count_100":129,"count_300":659,"count_50":0,"count_geki":0,"count_katu":0,"count_miss":10},"user_id":10750774,"score_id":137150917,"rank":"B","pp":62.6501},"91.4":{"maxcombo":463,"statistics":{"count_100":133,"count_300":663,"count_50":0,"count_geki":12,"count_katu":1,"count_miss":2},"user_id":28008413,"score_id":171630790,"rank":"B","pp":69.7352},"92.4":{"maxcombo":314,"statistics":{"count_100":69,"count_300":703,"count_50":0,"count_geki":0,"count_katu":0,"count_miss":26},"user_id":3084508,"score_id":160765731,"rank":"B","pp":62.7065}}