{"100":{"maxcombo":2496,"statistics":{"count_100":223,"count_300":2273,"count_50":383,"count_geki":353,"count_katu":0,"count_miss":0},"user_id":5220794,"score_id":199939087,"rank":"X","pp":801.204},"99.9":{"maxcombo":2496,"statistics":{"count_100":223,"count_300":2273,"count_50":382,"count_geki":353,"count_katu":1,"count_miss":0},"user_id":8172283,"score_id":204910015,"rank":"S","pp":799.675},"99.8":{"maxcombo":1366,"statistics":{"count_100":223,"count_300":2271,"count_50":380,"count_geki":351,"count_katu":3,"count_miss":2},"user_id":3171965,"score_id":201621665,"rank":"S","pp":460.999}}