{"96":{"maxcombo":479,"statistics":{"count_100":19,"count_300":299,"count_50":0,"count_geki":64,"count_katu":16,"count_miss":0},"user_id":8487136,"score_id":2802868621,"rank":"S","pp":103.821},"97":{"maxcombo":481,"statistics":{"count_100":14,"count_300":304,"count_50":0,"count_geki":69,"count_katu":11,"count_miss":0},"user_id":15435043,"score_id":4288432717,"rank":"S","pp":111.35},"99.1":{"maxcombo":482,"statistics":{"count_100":4,"count_300":314,"count_50":0,"count_geki":77,"count_katu":3,"count_miss":0},"user_id":12459123,"score_id":2785741052,"rank":"S","pp":136.599},"98.3":{"maxcombo":481,"statistics":{"count_100":8,"count_300":310,"count_50":0,"count_geki":72,"count_katu":8,"count_miss":0},"user_id":1403361,"score_id":3031771923,"rank":"S","pp":123.7},"99.5":{"maxcombo":481,"statistics":{"count_100":2,"count_300":316,"count_50":0,"count_geki":78,"count_katu":2,"count_miss":0},"user_id":4925835,"score_id":3334273669,"rank":"S","pp":144.226},"97.6":{"maxcombo":481,"statistics":{"count_100":11,"count_300":307,"count_50":0,"count_geki":73,"count_katu":7,"count_miss":0},"user_id":12335600,"score_id":3242487686,"rank":"S","pp":116.779},"97.1":{"maxcombo":434,"statistics":{"count_100":12,"count_300":305,"count_50":0,"count_geki":69,"count_katu":10,"count_miss":1},"user_id":12886299,"score_id":2810434658,"rank":"A","pp":98.7391},"97.2":{"maxcombo":481,"statistics":{"count_100":12,"count_300":305,"count_50":1,"count_geki":67,"count_katu":12,"count_miss":0},"user_id":11837846,"score_id":4330680402,"rank":"S","pp":112.489},"96.3":{"maxcombo":478,"statistics":{"count_100":16,"count_300":301,"count_50":1,"count_geki":66,"count_katu":13,"count_miss":0},"user_id":7635703,"score_id":3034723145,"rank":"S","pp":105.449},"96.4":{"maxcombo":476,"statistics":{"count_100":17,"count_300":301,"count_50":0,"count_geki":67,"count_katu":13,"count_miss":0},"user_id":19446642,"score_id":3845352168,"rank":"S","pp":105.194},"95.9":{"maxcombo":418,"statistics":{"count_100":18,"count_300":299,"count_50":0,"count_geki":66,"count_katu":13,"count_miss":1},"user_id":11029661,"score_id":3497427251,"rank":"A","pp":88.196},"95.8":{"maxcombo":470,"statistics":{"count_100":20,"count_300":298,"count_50":0,"count_geki":64,"count_katu":16,"count_miss":0},"user_id":20759873,"score_id":4471188795,"rank":"S","pp":100.11},"91.4":{"maxcombo":422,"statistics":{"count_100":38,"count_300":278,"count_50":0,"count_geki":52,"count_katu":26,"count_miss":2},"user_id":25894537,"score_id":4322580163,"rank":"B","pp":73.6572},"94.2":{"maxcombo":440,"statistics":{"count_100":26,"count_300":291,"count_50":0,"count_geki":57,"count_katu":22,"count_miss":1},"user_id":19950246,"score_id":4176136898,"rank":"A","pp":85.1428},"94.4":{"maxcombo":410,"statistics":{"count_100":22,"count_300":293,"count_50":1,"count_geki":60,"count_katu":18,"count_miss":2},"user_id":10061682,"score_id":3432127156,"rank":"A","pp":79.3116},"90.2":{"maxcombo":424,"statistics":{"count_100":40,"count_300":273,"count_50":4,"count_geki":51,"count_katu":24,"count_miss":1},"user_id":11545551,"score_id":3138142584,"rank":"B","pp":73.1468},"97.9":{"maxcombo":383,"statistics":{"count_100":7,"count_300":309,"count_50":0,"count_geki":72,"count_katu":6,"count_miss":2},"user_id":14690983,"score_id":3123890652,"rank":"A","pp":95.1126},"94.1":{"maxcombo":384,"statistics":{"count_100":28,"count_300":290,"count_50":0,"count_geki":62,"count_katu":18,"count_miss":0},"user_id":19672695,"score_id":4057644425,"rank":"S","pp":76.0306},"94.5":{"maxcombo":346,"statistics":{"count_100":23,"count_300":293,"count_50":0,"count_geki":61,"count_katu":17,"count_miss":2},"user_id":21199735,"score_id":4022801495,"rank":"A","pp":69.7981},"90.1":{"maxcombo":448,"statistics":{"count_100":43,"count_300":272,"count_50":2,"count_geki":47,"count_katu":30,"count_miss":1},"user_id":20663352,"score_id":3902354489,"rank":"B","pp":76.644},"91.9":{"maxcombo":332,"statistics":{"count_100":34,"count_300":281,"count_50":0,"count_geki":52,"count_katu":26,"count_miss":3},"user_id":14963611,"score_id":4255470710,"rank":"B","pp":59.3273},"95.4":{"maxcombo":324,"statistics":{"count_100":20,"count_300":297,"count_50":0,"count_geki":61,"count_katu":18,"count_miss":1},"user_id":13249483,"score_id":3022871876,"rank":"A","pp":70.6948},"93.4":{"maxcombo":386,"statistics":{"count_100":27,"count_300":288,"count_50":1,"count_geki":56,"count_katu":21,"count_miss":2},"user_id":3742570,"score_id":2926026940,"rank":"A","pp":72.8159},"91.5":{"maxcombo":364,"statistics":{"count_100":31,"count_300":280,"count_50":4,"count_geki":57,"count_katu":19,"count_miss":3},"user_id":19303944,"score_id":3580236165,"rank":"B","pp":62.6175},"95.1":{"maxcombo":357,"statistics":{"count_100":20,"count_300":296,"count_50":0,"count_geki":64,"count_katu":14,"count_miss":2},"user_id":31492250,"score_id":4370353893,"rank":"A","pp":73.6048}}