{"97":{"maxcombo":438,"statistics":{"count_100":14,"count_300":331,"count_50":0,"count_geki":54,"count_katu":11,"count_miss":1},"user_id":11994230,"score_id":3890418681,"rank":"A","pp":155.018},"94.2":{"maxcombo":511,"statistics":{"count_100":30,"count_300":316,"count_50":0,"count_geki":46,"count_katu":20,"count_miss":0},"user_id":17013765,"score_id":3668112610,"rank":"S","pp":151.102},"90.6":{"maxcombo":391,"statistics":{"count_100":42,"count_300":299,"count_50":3,"count_geki":37,"count_katu":26,"count_miss":2},"user_id":12368301,"score_id":4092405933,"rank":"B","pp":100.428}}