{"99.4":{"maxcombo":1146,"statistics":{"count_100":6,"count_300":707,"count_50":0,"count_geki":151,"count_katu":6,"count_miss":0},"user_id":15169131,"score_id":4035602447,"rank":"SH","pp":486.027},"99.2":{"maxcombo":1144,"statistics":{"count_100":8,"count_300":705,"count_50":0,"count_geki":150,"count_katu":7,"count_miss":0},"user_id":5400349,"score_id":4452411076,"rank":"SH","pp":474.123},"99.6":{"maxcombo":1084,"statistics":{"count_100":4,"count_300":709,"count_50":0,"count_geki":153,"count_katu":4,"count_miss":0},"user_id":4622337,"score_id":4074580460,"rank":"SH","pp":468.775},"99.1":{"maxcombo":1083,"statistics":{"count_100":8,"count_300":704,"count_50":0,"count_geki":152,"count_katu":4,"count_miss":1},"user_id":16829517,"score_id":4480056734,"rank":"A","pp":437.358},"97.9":{"maxcombo":1146,"statistics":{"count_100":22,"count_300":691,"count_50":0,"count_geki":142,"count_katu":15,"count_miss":0},"user_id":5206423,"score_id":4351882862,"rank":"SH","pp":416.199},"98.1":{"maxcombo":1058,"statistics":{"count_100":17,"count_300":694,"count_50":1,"count_geki":144,"count_katu":11,"count_miss":1},"user_id":4690632,"score_id":4000927001,"rank":"A","pp":387.444},"97.1":{"maxcombo":1041,"statistics":{"count_100":26,"count_300":684,"count_50":1,"count_geki":137,"count_katu":17,"count_miss":2},"user_id":12612018,"score_id":4421691070,"rank":"A","pp":348.146},"98.3":{"maxcombo":1001,"statistics":{"count_100":16,"count_300":696,"count_50":0,"count_geki":146,"count_katu":10,"count_miss":1},"user_id":15636237,"score_id":4476966806,"rank":"A","pp":381.502},"98.9":{"maxcombo":890,"statistics":{"count_100":11,"count_300":702,"count_50":0,"count_geki":149,"count_katu":8,"count_miss":0},"user_id":7159920,"score_id":4300285532,"rank":"SH","pp":380.934},"97.5":{"maxcombo":1065,"statistics":{"count_100":19,"count_300":689,"count_50":2,"count_geki":142,"count_katu":12,"count_miss":3},"user_id":5920715,"score_id":4321679026,"rank":"A","pp":357.865},"98.2":{"maxcombo":1081,"statistics":{"count_100":17,"count_300":695,"count_50":0,"count_geki":147,"count_katu":9,"count_miss":1},"user_id":5808807,"score_id":4385383343,"rank":"A","pp":397.597},"99.5":{"maxcombo":761,"statistics":{"count_100":2,"count_300":709,"count_50":0,"count_geki":153,"count_katu":2,"count_miss":2},"user_id":18119016,"score_id":4437735471,"rank":"A","pp":376.868}}