{"98":{"maxcombo":424,"statistics":{"count_100":11,"count_300":359,"count_50":0,"count_geki":99,"count_katu":8,"count_miss":0},"user_id":3738952,"score_id":3954076483,"rank":"S","pp":49.2795},"99":{"maxcombo":480,"statistics":{"count_100":5,"count_300":365,"count_50":0,"count_geki":104,"count_katu":3,"count_miss":0},"user_id":11317708,"score_id":4078254619,"rank":"S","pp":61.3785},"99.2":{"maxcombo":480,"statistics":{"count_100":4,"count_300":366,"count_50":0,"count_geki":103,"count_katu":4,"count_miss":0},"user_id":6922572,"score_id":2127629295,"rank":"S","pp":62.6654},"98.2":{"maxcombo":455,"statistics":{"count_100":7,"count_300":361,"count_50":1,"count_geki":98,"count_katu":7,"count_miss":1},"user_id":482949,"score_id":536716183,"rank":"A","pp":53.9025},"97.4":{"maxcombo":481,"statistics":{"count_100":14,"count_300":356,"count_50":0,"count_geki":97,"count_katu":10,"count_miss":0},"user_id":1603716,"score_id":1551527144,"rank":"S","pp":52.3253},"96.3":{"maxcombo":480,"statistics":{"count_100":20,"count_300":350,"count_50":0,"count_geki":89,"count_katu":18,"count_miss":0},"user_id":5342903,"score_id":1956893210,"rank":"S","pp":48.0055},"96.7":{"maxcombo":453,"statistics":{"count_100":15,"count_300":353,"count_50":0,"count_geki":95,"count_katu":11,"count_miss":2},"user_id":5813883,"score_id":1938424865,"rank":"A","pp":44.963},"97.6":{"maxcombo":477,"statistics":{"count_100":13,"count_300":357,"count_50":0,"count_geki":97,"count_katu":10,"count_miss":0},"user_id":16817215,"score_id":4048510416,"rank":"S","pp":52.8575},"98.3":{"maxcombo":480,"statistics":{"count_100":9,"count_300":361,"count_50":0,"count_geki":98,"count_katu":9,"count_miss":0},"user_id":5397691,"score_id":4388271979,"rank":"S","pp":56.8248},"95.6":{"maxcombo":481,"statistics":{"count_100":24,"count_300":346,"count_50":0,"count_geki":90,"count_katu":17,"count_miss":0},"user_id":14590860,"score_id":3177534829,"rank":"S","pp":45.8187},"98.1":{"maxcombo":481,"statistics":{"count_100":10,"count_300":360,"count_50":0,"count_geki":98,"count_katu":9,"count_miss":0},"user_id":16310722,"score_id":3310942918,"rank":"S","pp":55.8959},"95.1":{"maxcombo":481,"statistics":{"count_100":27,"count_300":343,"count_50":0,"count_geki":88,"count_katu":19,"count_miss":0},"user_id":16978130,"score_id":4445579325,"rank":"S","pp":44.3564},"98.4":{"maxcombo":457,"statistics":{"count_100":4,"count_300":363,"count_50":0,"count_geki":102,"count_katu":3,"count_miss":3},"user_id":18810302,"score_id":3792925293,"rank":"A","pp":51.8355}}